rtl/divu256.sv
// N-bit x N-bit divider (unsigned int)
module divu256
  #(parameter N = 256)  
  (
    input wire	       clk,
    input wire	       rst,
    input wire [N-1:0] divd, dvsr,
  
    output reg [N-1:0] val, rem, 
    output wire	       dbz,
    output reg [2:0]   state,
    output reg	       data_rdy
   );

  localparam reset = 2'h0;
  localparam active = 2'h1;
  localparam done = 2'h2;

  reg [$clog2(N):0] cnt;
  reg [2:0]	    n_state;
  
  reg [N:0]	    acc;
  reg [N-1:0]	    quo;
  
  always @(posedge clk or negedge rst) begin
    if (!rst)
      cnt <= '0;
    else if (state == done)
      cnt <= cnt;
    else
      cnt <= cnt + 1'b1;
  end
  
  // state logic
  always @(posedge clk or negedge rst) begin
    if (!rst)
      state <= reset;
    else
      state <= n_state;
  end
  
  assign n_state = (state == reset) ? active :
		   (cnt >= N) ? done :
		   (dbz) ? done : n_state;
  
  always @(posedge clk or negedge rst)
    data_rdy <= (!rst) ? '0 : (state == done && !dbz);  // data ready
  
  assign dbz = (rst) && (dvsr == 0);  // flag div by zero
  
  // division algorithm
  always @(posedge clk or negedge rst) begin: division_alg
    if (!rst)
      {acc, quo} <= '0;
    else if (dbz)
      {acc, quo} <= '0;
    else if (state == active) begin
      acc <= {(acc << 1) | divd[N-cnt +: 1]} >= dvsr ? {(acc << 1) | divd[N-cnt +: 1]} - dvsr : {(acc << 1) | divd[N-cnt +: 1]};
      
      quo <= {(acc << 1) | divd[N-cnt +: 1]} >= dvsr ? {(quo << 1) | 1'b1} : (quo << 1);
    end 
    else begin
      acc <= acc;
      quo <= quo;
    end 
  end // block: division_alg	     
  
  // quotient and remainder
  always @(posedge clk or negedge rst) begin
    if (!rst)
      {val, rem} <= '0;
    else if (dbz)
      {val, rem} <= '0;
    else if (state == done) begin
      val <= quo;
      rem <= acc;
    end else
      {val, rem} <= {val, rem};
  end
endmodule // divu255

rtl/tb/divu_tb.sv
// testbench for N-bit x N-bit divider
module divu_tb;
  reg          clk, rst;
  reg [255:0]  divd, dvsr;
  wire [255:0] val, rem;
  
  wire [2:0]   state;
  wire	       data_rdy;
  wire	       dbz;
  
  divu256 U0 (clk, rst, divd, dvsr, val, rem, dbz, state, data_rdy);
  
  initial begin
    $dumpfile("divu256.vcd");
    $dumpvars(0, divu_tb);
    clk = 0;
    rst = 0;
    divd = 0;
    dvsr = 0;
  end
  
  always #10 clk = ~clk;
  
  initial begin
    $monitor("%t: state: %d \ndata_rdy: %b \ndbz: %b \nval: %h \nrem: %h", $time, state, data_rdy, dbz, val, rem);
      
    $display("\n********************\nTEST 1: ’f/’f =  1 with rem 0\n********************\n");
    #10;
    divd = '1;
    dvsr = '1;
    rst = 1;
    
    #5120;

    #100;
    rst = 0;

    $display("\n********************\nTEST 2: 12/5 = 2 with rem 2\n********************\n");
    #100;
    divd = 12;
    dvsr = 5;
    rst = 1;

    #5120;
    
    #100;
    rst = 0;

    $display("\n********************\nTEST 3: divide by zero\n********************\n");
  // TEST 3: divide by zero
    #100;
    divd = 100;
    dvsr = 0;
    rst = 1;
    
    #5120;
    
    #100;
    rst = 0;

    $display("\n********************\nTEST 4: 5/7 = 0 with rem 5\n********************\n");
    #100;
    divd = 5;
    dvsr = 7;
    rst = 1;
    
    #5120;
    
    #100;
    rst = 0;

    $display("\n********************\nTEST 4: 45/9 = 5 with rem 0\n********************\n");
    #100;
    divd = 45;
    dvsr = 9;
    rst = 1;
    
    #5120;
    
    #100;
    $finish;
  end
endmodule

rtl/tb/waves/divu256.vcd
$date
	Sun Mar 24 00:49:07 2024
$end
$version
	Icarus Verilog
$end
$timescale
	1s
$end
$scope module divu_tb $end
$var wire 256 ! val [255:0] $end
$var wire 3 " state [2:0] $end
$var wire 256 # rem [255:0] $end
$var wire 1 $ dbz $end
$var wire 1 % data_rdy $end
$var reg 1 & clk $end
$var reg 256 ' divd [255:0] $end
$var reg 256 ( dvsr [255:0] $end
$var reg 1 ) rst $end
$scope module U0 $end
$var wire 1 & clk $end
$var wire 1 $ dbz $end
$var wire 256 * divd [255:0] $end
$var wire 256 + dvsr [255:0] $end
$var wire 1 ) rst $end
$var wire 3 , n_state [2:0] $end
$var parameter 32 - N $end
$var parameter 2 . active $end
$var parameter 2 / done $end
$var parameter 2 0 reset $end
$var reg 257 1 acc [256:0] $end
$var reg 9 2 cnt [8:0] $end
$var reg 1 % data_rdy $end
$var reg 256 3 quo [255:0] $end
$var reg 256 4 rem [255:0] $end
$var reg 3 5 state [2:0] $end
$var reg 256 6 val [255:0] $end
$scope begin division_alg $end
$upscope $end
$upscope $end
$upscope $end
$enddefinitions $end
$comment Show the parameter values. $end
$dumpall
b0 0
b10 /
b1 .
b100000000 -
$end
#0
$dumpvars
b0 6
b0 5
b0 4
b0 3
b0 2
b0 1
b1 ,
b0 +
b0 *
0)
b0 (
b0 '
0&
0%
0$
b0 #
b0 "
b0 !
$end
#10
b1 "
b1 5
b1 2
1)
b1111111111111111111111111111111111111111111111111111111111111111111111111111111111111111111111111111111111111111111111111111111111111111111111111111111111111111111111111111111111111111111111111111111111111111111111111111111111111111111111111111111111111111 (
b1111111111111111111111111111111111111111111111111111111111111111111111111111111111111111111111111111111111111111111111111111111111111111111111111111111111111111111111111111111111111111111111111111111111111111111111111111111111111111111111111111111111111111 +
b1111111111111111111111111111111111111111111111111111111111111111111111111111111111111111111111111111111111111111111111111111111111111111111111111111111111111111111111111111111111111111111111111111111111111111111111111111111111111111111111111111111111111111 '
b1111111111111111111111111111111111111111111111111111111111111111111111111111111111111111111111111111111111111111111111111111111111111111111111111111111111111111111111111111111111111111111111111111111111111111111111111111111111111111111111111111111111111111 *
1&
#20
0&
#30
b1 1
b10 2
1&
#40
0&
#50
b11 1
b11 2
1&
#60
0&
#70
b111 1
b100 2
1&
#80
0&
#90
b1111 1
b101 2
1&
#100
0&
#110
b11111 1
b110 2
1&
#120
0&
#130
b111111 1
b111 2
1&
#140
0&
#150
b1111111 1
b1000 2
1&
#160
0&
#170
b11111111 1
b1001 2
1&
#180
0&
#190
b111111111 1
b1010 2
1&
#200
0&
#210
b1111111111 1
b1011 2
1&
#220
0&
#230
b11111111111 1
b1100 2
1&
#240
0&
#250
b111111111111 1
b1101 2
1&
#260
0&
#270
b1111111111111 1
b1110 2
1&
#280
0&
#290
b11111111111111 1
b1111 2
1&
#300
0&
#310
b111111111111111 1
b10000 2
1&
#320
0&
#330
b1111111111111111 1
b10001 2
1&
#340
0&
#350
b11111111111111111 1
b10010 2
1&
#360
0&
#370
b111111111111111111 1
b10011 2
1&
#380
0&
#390
b1111111111111111111 1
b10100 2
1&
#400
0&
#410
b11111111111111111111 1
b10101 2
1&
#420
0&
#430
b111111111111111111111 1
b10110 2
1&
#440
0&
#450
b1111111111111111111111 1
b10111 2
1&
#460
0&
#470
b11111111111111111111111 1
b11000 2
1&
#480
0&
#490
b111111111111111111111111 1
b11001 2
1&
#500
0&
#510
b1111111111111111111111111 1
b11010 2
1&
#520
0&
#530
b11111111111111111111111111 1
b11011 2
1&
#540
0&
#550
b111111111111111111111111111 1
b11100 2
1&
#560
0&
#570
b1111111111111111111111111111 1
b11101 2
1&
#580
0&
#590
b11111111111111111111111111111 1
b11110 2
1&
#600
0&
#610
b111111111111111111111111111111 1
b11111 2
1&
#620
0&
#630
b1111111111111111111111111111111 1
b100000 2
1&
#640
0&
#650
b11111111111111111111111111111111 1
b100001 2
1&
#660
0&
#670
b111111111111111111111111111111111 1
b100010 2
1&
#680
0&
#690
b1111111111111111111111111111111111 1
b100011 2
1&
#700
0&
#710
b11111111111111111111111111111111111 1
b100100 2
1&
#720
0&
#730
b111111111111111111111111111111111111 1
b100101 2
1&
#740
0&
#750
b1111111111111111111111111111111111111 1
b100110 2
1&
#760
0&
#770
b11111111111111111111111111111111111111 1
b100111 2
1&
#780
0&
#790
b111111111111111111111111111111111111111 1
b101000 2
1&
#800
0&
#810
b1111111111111111111111111111111111111111 1
b101001 2
1&
#820
0&
#830
b11111111111111111111111111111111111111111 1
b101010 2
1&
#840
0&
#850
b111111111111111111111111111111111111111111 1
b101011 2
1&
#860
0&
#870
b1111111111111111111111111111111111111111111 1
b101100 2
1&
#880
0&
#890
b11111111111111111111111111111111111111111111 1
b101101 2
1&
#900
0&
#910
b111111111111111111111111111111111111111111111 1
b101110 2
1&
#920
0&
#930
b1111111111111111111111111111111111111111111111 1
b101111 2
1&
#940
0&
#950
b11111111111111111111111111111111111111111111111 1
b110000 2
1&
#960
0&
#970
b111111111111111111111111111111111111111111111111 1
b110001 2
1&
#980
0&
#990
b1111111111111111111111111111111111111111111111111 1
b110010 2
1&
#1000
0&
#1010
b11111111111111111111111111111111111111111111111111 1
b110011 2
1&
#1020
0&
#1030
b111111111111111111111111111111111111111111111111111 1
b110100 2
1&
#1040
0&
#1050
b1111111111111111111111111111111111111111111111111111 1
b110101 2
1&
#1060
0&
#1070
b11111111111111111111111111111111111111111111111111111 1
b110110 2
1&
#1080
0&
#1090
b111111111111111111111111111111111111111111111111111111 1
b110111 2
1&
#1100
0&
#1110
b1111111111111111111111111111111111111111111111111111111 1
b111000 2
1&
#1120
0&
#1130
b11111111111111111111111111111111111111111111111111111111 1
b111001 2
1&
#1140
0&
#1150
b111111111111111111111111111111111111111111111111111111111 1
b111010 2
1&
#1160
0&
#1170
b1111111111111111111111111111111111111111111111111111111111 1
b111011 2
1&
#1180
0&
#1190
b11111111111111111111111111111111111111111111111111111111111 1
b111100 2
1&
#1200
0&
#1210
b111111111111111111111111111111111111111111111111111111111111 1
b111101 2
1&
#1220
0&
#1230
b1111111111111111111111111111111111111111111111111111111111111 1
b111110 2
1&
#1240
0&
#1250
b11111111111111111111111111111111111111111111111111111111111111 1
b111111 2
1&
#1260
0&
#1270
b111111111111111111111111111111111111111111111111111111111111111 1
b1000000 2
1&
#1280
0&
#1290
b1111111111111111111111111111111111111111111111111111111111111111 1
b1000001 2
1&
#1300
0&
#1310
b11111111111111111111111111111111111111111111111111111111111111111 1
b1000010 2
1&
#1320
0&
#1330
b111111111111111111111111111111111111111111111111111111111111111111 1
b1000011 2
1&
#1340
0&
#1350
b1111111111111111111111111111111111111111111111111111111111111111111 1
b1000100 2
1&
#1360
0&
#1370
b11111111111111111111111111111111111111111111111111111111111111111111 1
b1000101 2
1&
#1380
0&
#1390
b111111111111111111111111111111111111111111111111111111111111111111111 1
b1000110 2
1&
#1400
0&
#1410
b1111111111111111111111111111111111111111111111111111111111111111111111 1
b1000111 2
1&
#1420
0&
#1430
b11111111111111111111111111111111111111111111111111111111111111111111111 1
b1001000 2
1&
#1440
0&
#1450
b111111111111111111111111111111111111111111111111111111111111111111111111 1
b1001001 2
1&
#1460
0&
#1470
b1111111111111111111111111111111111111111111111111111111111111111111111111 1
b1001010 2
1&
#1480
0&
#1490
b11111111111111111111111111111111111111111111111111111111111111111111111111 1
b1001011 2
1&
#1500
0&
#1510
b111111111111111111111111111111111111111111111111111111111111111111111111111 1
b1001100 2
1&
#1520
0&
#1530
b1111111111111111111111111111111111111111111111111111111111111111111111111111 1
b1001101 2
1&
#1540
0&
#1550
b11111111111111111111111111111111111111111111111111111111111111111111111111111 1
b1001110 2
1&
#1560
0&
#1570
b111111111111111111111111111111111111111111111111111111111111111111111111111111 1
b1001111 2
1&
#1580
0&
#1590
b1111111111111111111111111111111111111111111111111111111111111111111111111111111 1
b1010000 2
1&
#1600
0&
#1610
b11111111111111111111111111111111111111111111111111111111111111111111111111111111 1
b1010001 2
1&
#1620
0&
#1630
b111111111111111111111111111111111111111111111111111111111111111111111111111111111 1
b1010010 2
1&
#1640
0&
#1650
b1111111111111111111111111111111111111111111111111111111111111111111111111111111111 1
b1010011 2
1&
#1660
0&
#1670
b11111111111111111111111111111111111111111111111111111111111111111111111111111111111 1
b1010100 2
1&
#1680
0&
#1690
b111111111111111111111111111111111111111111111111111111111111111111111111111111111111 1
b1010101 2
1&
#1700
0&
#1710
b1111111111111111111111111111111111111111111111111111111111111111111111111111111111111 1
b1010110 2
1&
#1720
0&
#1730
b11111111111111111111111111111111111111111111111111111111111111111111111111111111111111 1
b1010111 2
1&
#1740
0&
#1750
b111111111111111111111111111111111111111111111111111111111111111111111111111111111111111 1
b1011000 2
1&
#1760
0&
#1770
b1111111111111111111111111111111111111111111111111111111111111111111111111111111111111111 1
b1011001 2
1&
#1780
0&
#1790
b11111111111111111111111111111111111111111111111111111111111111111111111111111111111111111 1
b1011010 2
1&
#1800
0&
#1810
b111111111111111111111111111111111111111111111111111111111111111111111111111111111111111111 1
b1011011 2
1&
#1820
0&
#1830
b1111111111111111111111111111111111111111111111111111111111111111111111111111111111111111111 1
b1011100 2
1&
#1840
0&
#1850
b11111111111111111111111111111111111111111111111111111111111111111111111111111111111111111111 1
b1011101 2
1&
#1860
0&
#1870
b111111111111111111111111111111111111111111111111111111111111111111111111111111111111111111111 1
b1011110 2
1&
#1880
0&
#1890
b1111111111111111111111111111111111111111111111111111111111111111111111111111111111111111111111 1
b1011111 2
1&
#1900
0&
#1910
b11111111111111111111111111111111111111111111111111111111111111111111111111111111111111111111111 1
b1100000 2
1&
#1920
0&
#1930
b111111111111111111111111111111111111111111111111111111111111111111111111111111111111111111111111 1
b1100001 2
1&
#1940
0&
#1950
b1111111111111111111111111111111111111111111111111111111111111111111111111111111111111111111111111 1
b1100010 2
1&
#1960
0&
#1970
b11111111111111111111111111111111111111111111111111111111111111111111111111111111111111111111111111 1
b1100011 2
1&
#1980
0&
#1990
b111111111111111111111111111111111111111111111111111111111111111111111111111111111111111111111111111 1
b1100100 2
1&
#2000
0&
#2010
b1111111111111111111111111111111111111111111111111111111111111111111111111111111111111111111111111111 1
b1100101 2
1&
#2020
0&
#2030
b11111111111111111111111111111111111111111111111111111111111111111111111111111111111111111111111111111 1
b1100110 2
1&
#2040
0&
#2050
b111111111111111111111111111111111111111111111111111111111111111111111111111111111111111111111111111111 1
b1100111 2
1&
#2060
0&
#2070
b1111111111111111111111111111111111111111111111111111111111111111111111111111111111111111111111111111111 1
b1101000 2
1&
#2080
0&
#2090
b11111111111111111111111111111111111111111111111111111111111111111111111111111111111111111111111111111111 1
b1101001 2
1&
#2100
0&
#2110
b111111111111111111111111111111111111111111111111111111111111111111111111111111111111111111111111111111111 1
b1101010 2
1&
#2120
0&
#2130
b1111111111111111111111111111111111111111111111111111111111111111111111111111111111111111111111111111111111 1
b1101011 2
1&
#2140
0&
#2150
b11111111111111111111111111111111111111111111111111111111111111111111111111111111111111111111111111111111111 1
b1101100 2
1&
#2160
0&
#2170
b111111111111111111111111111111111111111111111111111111111111111111111111111111111111111111111111111111111111 1
b1101101 2
1&
#2180
0&
#2190
b1111111111111111111111111111111111111111111111111111111111111111111111111111111111111111111111111111111111111 1
b1101110 2
1&
#2200
0&
#2210
b11111111111111111111111111111111111111111111111111111111111111111111111111111111111111111111111111111111111111 1
b1101111 2
1&
#2220
0&
#2230
b111111111111111111111111111111111111111111111111111111111111111111111111111111111111111111111111111111111111111 1
b1110000 2
1&
#2240
0&
#2250
b1111111111111111111111111111111111111111111111111111111111111111111111111111111111111111111111111111111111111111 1
b1110001 2
1&
#2260
0&
#2270
b11111111111111111111111111111111111111111111111111111111111111111111111111111111111111111111111111111111111111111 1
b1110010 2
1&
#2280
0&
#2290
b111111111111111111111111111111111111111111111111111111111111111111111111111111111111111111111111111111111111111111 1
b1110011 2
1&
#2300
0&
#2310
b1111111111111111111111111111111111111111111111111111111111111111111111111111111111111111111111111111111111111111111 1
b1110100 2
1&
#2320
0&
#2330
b11111111111111111111111111111111111111111111111111111111111111111111111111111111111111111111111111111111111111111111 1
b1110101 2
1&
#2340
0&
#2350
b111111111111111111111111111111111111111111111111111111111111111111111111111111111111111111111111111111111111111111111 1
b1110110 2
1&
#2360
0&
#2370
b1111111111111111111111111111111111111111111111111111111111111111111111111111111111111111111111111111111111111111111111 1
b1110111 2
1&
#2380
0&
#2390
b11111111111111111111111111111111111111111111111111111111111111111111111111111111111111111111111111111111111111111111111 1
b1111000 2
1&
#2400
0&
#2410
b111111111111111111111111111111111111111111111111111111111111111111111111111111111111111111111111111111111111111111111111 1
b1111001 2
1&
#2420
0&
#2430
b1111111111111111111111111111111111111111111111111111111111111111111111111111111111111111111111111111111111111111111111111 1
b1111010 2
1&
#2440
0&
#2450
b11111111111111111111111111111111111111111111111111111111111111111111111111111111111111111111111111111111111111111111111111 1
b1111011 2
1&
#2460
0&
#2470
b111111111111111111111111111111111111111111111111111111111111111111111111111111111111111111111111111111111111111111111111111 1
b1111100 2
1&
#2480
0&
#2490
b1111111111111111111111111111111111111111111111111111111111111111111111111111111111111111111111111111111111111111111111111111 1
b1111101 2
1&
#2500
0&
#2510
b11111111111111111111111111111111111111111111111111111111111111111111111111111111111111111111111111111111111111111111111111111 1
b1111110 2
1&
#2520
0&
#2530
b111111111111111111111111111111111111111111111111111111111111111111111111111111111111111111111111111111111111111111111111111111 1
b1111111 2
1&
#2540
0&
#2550
b1111111111111111111111111111111111111111111111111111111111111111111111111111111111111111111111111111111111111111111111111111111 1
b10000000 2
1&
#2560
0&
#2570
b11111111111111111111111111111111111111111111111111111111111111111111111111111111111111111111111111111111111111111111111111111111 1
b10000001 2
1&
#2580
0&
#2590
b111111111111111111111111111111111111111111111111111111111111111111111111111111111111111111111111111111111111111111111111111111111 1
b10000010 2
1&
#2600
0&
#2610
b1111111111111111111111111111111111111111111111111111111111111111111111111111111111111111111111111111111111111111111111111111111111 1
b10000011 2
1&
#2620
0&
#2630
b11111111111111111111111111111111111111111111111111111111111111111111111111111111111111111111111111111111111111111111111111111111111 1
b10000100 2
1&
#2640
0&
#2650
b111111111111111111111111111111111111111111111111111111111111111111111111111111111111111111111111111111111111111111111111111111111111 1
b10000101 2
1&
#2660
0&
#2670
b1111111111111111111111111111111111111111111111111111111111111111111111111111111111111111111111111111111111111111111111111111111111111 1
b10000110 2
1&
#2680
0&
#2690
b11111111111111111111111111111111111111111111111111111111111111111111111111111111111111111111111111111111111111111111111111111111111111 1
b10000111 2
1&
#2700
0&
#2710
b111111111111111111111111111111111111111111111111111111111111111111111111111111111111111111111111111111111111111111111111111111111111111 1
b10001000 2
1&
#2720
0&
#2730
b1111111111111111111111111111111111111111111111111111111111111111111111111111111111111111111111111111111111111111111111111111111111111111 1
b10001001 2
1&
#2740
0&
#2750
b11111111111111111111111111111111111111111111111111111111111111111111111111111111111111111111111111111111111111111111111111111111111111111 1
b10001010 2
1&
#2760
0&
#2770
b111111111111111111111111111111111111111111111111111111111111111111111111111111111111111111111111111111111111111111111111111111111111111111 1
b10001011 2
1&
#2780
0&
#2790
b1111111111111111111111111111111111111111111111111111111111111111111111111111111111111111111111111111111111111111111111111111111111111111111 1
b10001100 2
1&
#2800
0&
#2810
b11111111111111111111111111111111111111111111111111111111111111111111111111111111111111111111111111111111111111111111111111111111111111111111 1
b10001101 2
1&
#2820
0&
#2830
b111111111111111111111111111111111111111111111111111111111111111111111111111111111111111111111111111111111111111111111111111111111111111111111 1
b10001110 2
1&
#2840
0&
#2850
b1111111111111111111111111111111111111111111111111111111111111111111111111111111111111111111111111111111111111111111111111111111111111111111111 1
b10001111 2
1&
#2860
0&
#2870
b11111111111111111111111111111111111111111111111111111111111111111111111111111111111111111111111111111111111111111111111111111111111111111111111 1
b10010000 2
1&
#2880
0&
#2890
b111111111111111111111111111111111111111111111111111111111111111111111111111111111111111111111111111111111111111111111111111111111111111111111111 1
b10010001 2
1&
#2900
0&
#2910
b1111111111111111111111111111111111111111111111111111111111111111111111111111111111111111111111111111111111111111111111111111111111111111111111111 1
b10010010 2
1&
#2920
0&
#2930
b11111111111111111111111111111111111111111111111111111111111111111111111111111111111111111111111111111111111111111111111111111111111111111111111111 1
b10010011 2
1&
#2940
0&
#2950
b111111111111111111111111111111111111111111111111111111111111111111111111111111111111111111111111111111111111111111111111111111111111111111111111111 1
b10010100 2
1&
#2960
0&
#2970
b1111111111111111111111111111111111111111111111111111111111111111111111111111111111111111111111111111111111111111111111111111111111111111111111111111 1
b10010101 2
1&
#2980
0&
#2990
b11111111111111111111111111111111111111111111111111111111111111111111111111111111111111111111111111111111111111111111111111111111111111111111111111111 1
b10010110 2
1&
#3000
0&
#3010
b111111111111111111111111111111111111111111111111111111111111111111111111111111111111111111111111111111111111111111111111111111111111111111111111111111 1
b10010111 2
1&
#3020
0&
#3030
b1111111111111111111111111111111111111111111111111111111111111111111111111111111111111111111111111111111111111111111111111111111111111111111111111111111 1
b10011000 2
1&
#3040
0&
#3050
b11111111111111111111111111111111111111111111111111111111111111111111111111111111111111111111111111111111111111111111111111111111111111111111111111111111 1
b10011001 2
1&
#3060
0&
#3070
b111111111111111111111111111111111111111111111111111111111111111111111111111111111111111111111111111111111111111111111111111111111111111111111111111111111 1
b10011010 2
1&
#3080
0&
#3090
b1111111111111111111111111111111111111111111111111111111111111111111111111111111111111111111111111111111111111111111111111111111111111111111111111111111111 1
b10011011 2
1&
#3100
0&
#3110
b11111111111111111111111111111111111111111111111111111111111111111111111111111111111111111111111111111111111111111111111111111111111111111111111111111111111 1
b10011100 2
1&
#3120
0&
#3130
b111111111111111111111111111111111111111111111111111111111111111111111111111111111111111111111111111111111111111111111111111111111111111111111111111111111111 1
b10011101 2
1&
#3140
0&
#3150
b1111111111111111111111111111111111111111111111111111111111111111111111111111111111111111111111111111111111111111111111111111111111111111111111111111111111111 1
b10011110 2
1&
#3160
0&
#3170
b11111111111111111111111111111111111111111111111111111111111111111111111111111111111111111111111111111111111111111111111111111111111111111111111111111111111111 1
b10011111 2
1&
#3180
0&
#3190
b111111111111111111111111111111111111111111111111111111111111111111111111111111111111111111111111111111111111111111111111111111111111111111111111111111111111111 1
b10100000 2
1&
#3200
0&
#3210
b1111111111111111111111111111111111111111111111111111111111111111111111111111111111111111111111111111111111111111111111111111111111111111111111111111111111111111 1
b10100001 2
1&
#3220
0&
#3230
b11111111111111111111111111111111111111111111111111111111111111111111111111111111111111111111111111111111111111111111111111111111111111111111111111111111111111111 1
b10100010 2
1&
#3240
0&
#3250
b111111111111111111111111111111111111111111111111111111111111111111111111111111111111111111111111111111111111111111111111111111111111111111111111111111111111111111 1
b10100011 2
1&
#3260
0&
#3270
b1111111111111111111111111111111111111111111111111111111111111111111111111111111111111111111111111111111111111111111111111111111111111111111111111111111111111111111 1
b10100100 2
1&
#3280
0&
#3290
b11111111111111111111111111111111111111111111111111111111111111111111111111111111111111111111111111111111111111111111111111111111111111111111111111111111111111111111 1
b10100101 2
1&
#3300
0&
#3310
b111111111111111111111111111111111111111111111111111111111111111111111111111111111111111111111111111111111111111111111111111111111111111111111111111111111111111111111 1
b10100110 2
1&
#3320
0&
#3330
b1111111111111111111111111111111111111111111111111111111111111111111111111111111111111111111111111111111111111111111111111111111111111111111111111111111111111111111111 1
b10100111 2
1&
#3340
0&
#3350
b11111111111111111111111111111111111111111111111111111111111111111111111111111111111111111111111111111111111111111111111111111111111111111111111111111111111111111111111 1
b10101000 2
1&
#3360
0&
#3370
b111111111111111111111111111111111111111111111111111111111111111111111111111111111111111111111111111111111111111111111111111111111111111111111111111111111111111111111111 1
b10101001 2
1&
#3380
0&
#3390
b1111111111111111111111111111111111111111111111111111111111111111111111111111111111111111111111111111111111111111111111111111111111111111111111111111111111111111111111111 1
b10101010 2
1&
#3400
0&
#3410
b11111111111111111111111111111111111111111111111111111111111111111111111111111111111111111111111111111111111111111111111111111111111111111111111111111111111111111111111111 1
b10101011 2
1&
#3420
0&
#3430
b111111111111111111111111111111111111111111111111111111111111111111111111111111111111111111111111111111111111111111111111111111111111111111111111111111111111111111111111111 1
b10101100 2
1&
#3440
0&
#3450
b1111111111111111111111111111111111111111111111111111111111111111111111111111111111111111111111111111111111111111111111111111111111111111111111111111111111111111111111111111 1
b10101101 2
1&
#3460
0&
#3470
b11111111111111111111111111111111111111111111111111111111111111111111111111111111111111111111111111111111111111111111111111111111111111111111111111111111111111111111111111111 1
b10101110 2
1&
#3480
0&
#3490
b111111111111111111111111111111111111111111111111111111111111111111111111111111111111111111111111111111111111111111111111111111111111111111111111111111111111111111111111111111 1
b10101111 2
1&
#3500
0&
#3510
b1111111111111111111111111111111111111111111111111111111111111111111111111111111111111111111111111111111111111111111111111111111111111111111111111111111111111111111111111111111 1
b10110000 2
1&
#3520
0&
#3530
b11111111111111111111111111111111111111111111111111111111111111111111111111111111111111111111111111111111111111111111111111111111111111111111111111111111111111111111111111111111 1
b10110001 2
1&
#3540
0&
#3550
b111111111111111111111111111111111111111111111111111111111111111111111111111111111111111111111111111111111111111111111111111111111111111111111111111111111111111111111111111111111 1
b10110010 2
1&
#3560
0&
#3570
b1111111111111111111111111111111111111111111111111111111111111111111111111111111111111111111111111111111111111111111111111111111111111111111111111111111111111111111111111111111111 1
b10110011 2
1&
#3580
0&
#3590
b11111111111111111111111111111111111111111111111111111111111111111111111111111111111111111111111111111111111111111111111111111111111111111111111111111111111111111111111111111111111 1
b10110100 2
1&
#3600
0&
#3610
b111111111111111111111111111111111111111111111111111111111111111111111111111111111111111111111111111111111111111111111111111111111111111111111111111111111111111111111111111111111111 1
b10110101 2
1&
#3620
0&
#3630
b1111111111111111111111111111111111111111111111111111111111111111111111111111111111111111111111111111111111111111111111111111111111111111111111111111111111111111111111111111111111111 1
b10110110 2
1&
#3640
0&
#3650
b11111111111111111111111111111111111111111111111111111111111111111111111111111111111111111111111111111111111111111111111111111111111111111111111111111111111111111111111111111111111111 1
b10110111 2
1&
#3660
0&
#3670
b111111111111111111111111111111111111111111111111111111111111111111111111111111111111111111111111111111111111111111111111111111111111111111111111111111111111111111111111111111111111111 1
b10111000 2
1&
#3680
0&
#3690
b1111111111111111111111111111111111111111111111111111111111111111111111111111111111111111111111111111111111111111111111111111111111111111111111111111111111111111111111111111111111111111 1
b10111001 2
1&
#3700
0&
#3710
b11111111111111111111111111111111111111111111111111111111111111111111111111111111111111111111111111111111111111111111111111111111111111111111111111111111111111111111111111111111111111111 1
b10111010 2
1&
#3720
0&
#3730
b111111111111111111111111111111111111111111111111111111111111111111111111111111111111111111111111111111111111111111111111111111111111111111111111111111111111111111111111111111111111111111 1
b10111011 2
1&
#3740
0&
#3750
b1111111111111111111111111111111111111111111111111111111111111111111111111111111111111111111111111111111111111111111111111111111111111111111111111111111111111111111111111111111111111111111 1
b10111100 2
1&
#3760
0&
#3770
b11111111111111111111111111111111111111111111111111111111111111111111111111111111111111111111111111111111111111111111111111111111111111111111111111111111111111111111111111111111111111111111 1
b10111101 2
1&
#3780
0&
#3790
b111111111111111111111111111111111111111111111111111111111111111111111111111111111111111111111111111111111111111111111111111111111111111111111111111111111111111111111111111111111111111111111 1
b10111110 2
1&
#3800
0&
#3810
b1111111111111111111111111111111111111111111111111111111111111111111111111111111111111111111111111111111111111111111111111111111111111111111111111111111111111111111111111111111111111111111111 1
b10111111 2
1&
#3820
0&
#3830
b11111111111111111111111111111111111111111111111111111111111111111111111111111111111111111111111111111111111111111111111111111111111111111111111111111111111111111111111111111111111111111111111 1
b11000000 2
1&
#3840
0&
#3850
b111111111111111111111111111111111111111111111111111111111111111111111111111111111111111111111111111111111111111111111111111111111111111111111111111111111111111111111111111111111111111111111111 1
b11000001 2
1&
#3860
0&
#3870
b1111111111111111111111111111111111111111111111111111111111111111111111111111111111111111111111111111111111111111111111111111111111111111111111111111111111111111111111111111111111111111111111111 1
b11000010 2
1&
#3880
0&
#3890
b11111111111111111111111111111111111111111111111111111111111111111111111111111111111111111111111111111111111111111111111111111111111111111111111111111111111111111111111111111111111111111111111111 1
b11000011 2
1&
#3900
0&
#3910
b111111111111111111111111111111111111111111111111111111111111111111111111111111111111111111111111111111111111111111111111111111111111111111111111111111111111111111111111111111111111111111111111111 1
b11000100 2
1&
#3920
0&
#3930
b1111111111111111111111111111111111111111111111111111111111111111111111111111111111111111111111111111111111111111111111111111111111111111111111111111111111111111111111111111111111111111111111111111 1
b11000101 2
1&
#3940
0&
#3950
b11111111111111111111111111111111111111111111111111111111111111111111111111111111111111111111111111111111111111111111111111111111111111111111111111111111111111111111111111111111111111111111111111111 1
b11000110 2
1&
#3960
0&
#3970
b111111111111111111111111111111111111111111111111111111111111111111111111111111111111111111111111111111111111111111111111111111111111111111111111111111111111111111111111111111111111111111111111111111 1
b11000111 2
1&
#3980
0&
#3990
b1111111111111111111111111111111111111111111111111111111111111111111111111111111111111111111111111111111111111111111111111111111111111111111111111111111111111111111111111111111111111111111111111111111 1
b11001000 2
1&
#4000
0&
#4010
b11111111111111111111111111111111111111111111111111111111111111111111111111111111111111111111111111111111111111111111111111111111111111111111111111111111111111111111111111111111111111111111111111111111 1
b11001001 2
1&
#4020
0&
#4030
b111111111111111111111111111111111111111111111111111111111111111111111111111111111111111111111111111111111111111111111111111111111111111111111111111111111111111111111111111111111111111111111111111111111 1
b11001010 2
1&
#4040
0&
#4050
b1111111111111111111111111111111111111111111111111111111111111111111111111111111111111111111111111111111111111111111111111111111111111111111111111111111111111111111111111111111111111111111111111111111111 1
b11001011 2
1&
#4060
0&
#4070
b11111111111111111111111111111111111111111111111111111111111111111111111111111111111111111111111111111111111111111111111111111111111111111111111111111111111111111111111111111111111111111111111111111111111 1
b11001100 2
1&
#4080
0&
#4090
b111111111111111111111111111111111111111111111111111111111111111111111111111111111111111111111111111111111111111111111111111111111111111111111111111111111111111111111111111111111111111111111111111111111111 1
b11001101 2
1&
#4100
0&
#4110
b1111111111111111111111111111111111111111111111111111111111111111111111111111111111111111111111111111111111111111111111111111111111111111111111111111111111111111111111111111111111111111111111111111111111111 1
b11001110 2
1&
#4120
0&
