rtl/divu256.sv
// N-bit x N-bit divider (unsigned int)
module divu256
  #(parameter N = 256)  
  (
    input wire	       clk,
    input wire	       rst,
    input wire [N-1:0] divd, dvsr,
  
    output reg [N-1:0] val, rem, 
    output wire	       dbz,
    output reg [2:0]   state,
    output reg	       data_rdy
   );

  localparam reset = 2'h0;
  localparam active = 2'h1;
  localparam done = 2'h2;

  reg [$clog2(N):0] cnt;
  reg [2:0]	    n_state;
  
  reg [N:0]	    acc;
  reg [N-1:0]	    quo;
  
  always @(posedge clk or negedge rst) begin
    if (!rst)
      cnt <= '0;
    else if (state == done)
      cnt <= cnt;
    else
      cnt <= cnt + 1'b1;
  end
  
  // state logic
  always @(posedge clk or negedge rst) begin
    if (!rst)
      state <= reset;
    else
      state <= n_state;
  end
  
  assign n_state = (state == reset) ? active :
		   (cnt >= N) ? done :
		   (dbz) ? done : n_state;
  
  always @(posedge clk or negedge rst)
    data_rdy <= (!rst) ? '0 : (state == done && !dbz);  // data ready
  
  assign dbz = (rst) && (dvsr == 0);  // flag div by zero
  
  // division algorithm
  always @(posedge clk or negedge rst) begin: division_alg
    if (!rst)
      {acc, quo} <= '0;
    else if (dbz)
      {acc, quo} <= '0;
    else if (state == active) begin
      acc <= {(acc << 1) | divd[N-cnt +: 1]} >= dvsr ? {(acc << 1) | divd[N-cnt +: 1]} - dvsr : {(acc << 1) | divd[N-cnt +: 1]};
      
      quo <= {(acc << 1) | divd[N-cnt +: 1]} >= dvsr ? {(quo << 1) | 1'b1} : (quo << 1);
    end 
    else begin
      acc <= acc;
      quo <= quo;
    end 
  end // block: division_alg	     
  
  // quotient and remainder
  always @(posedge clk or negedge rst) begin
    if (!rst)
      {val, rem} <= '0;
    else if (dbz)
      {val, rem} <= '0;
    else if (state == done) begin
      val <= quo;
      rem <= acc;
    end else
      {val, rem} <= {val, rem};
  end
endmodule // divu255

rtl/mod_p.sv
// reduction modulo q = 2^255 - 19
//  - returns b in  a == b  (mod q) 
module mod_q 
  #(parameter N = 256)
  (
   input wire	      clk, rst_n,
   input wire [N-1:0] a, 
   
   output reg [N-1:0]  b
   );

  reg [N-1:0] q = 256'h7fffffffffffffffffffffffffffffffffffffffffffffffffffffffffffffff;
  
  reg [N-1:0] divd, val;
  
  wire [N-1:0] r;
  
  wire [2:0]  st;
  wire	      dbz;
  reg	      busy;
  wire	      data_rdy;
	      
  divu256 U0 (.clk(clk), .rst(rst_n), 
	      .divd(divd), .dvsr(q), .val(val), .rem(r), 
	      .dbz(dbz), .state(st), .data_rdy(data_rdy));
	      
  always_comb
    if (!rst_n) begin
      busy = 0;
      divd = 0;
    end
    else if (!busy) begin
      busy = 1;
      divd = a;
    end else begin
      busy = busy;
      divd = divd;
    end 
 
  // result
  always_comb
    if (!rst_n)
      b = 0;
    else if (!busy || (st != 2 && !data_rdy))
      b = 0;
    else
      b = val; 

endmodule

rtl/tb/mod_q_tb.sv
// testbench for reduction modulo q module 
module mod_q_tb #(parameter N = 256);
  reg [N-1:0] a;
  reg [N-1:0] b;
  reg	    clk, rst_n;
 
  mod_q U0 (clk, rst_n, a, b);

  initial begin
    $dumpfile("mod_q.vcd");
    $dumpvars(0, mod_q_tb);
    
    clk = 0;
    rst_n = 0;
    a = 0;
  end
  
  always #10 clk = ~clk;

  initial begin
    $monitor("%t: \n rst_n: %d \n a: %h \n b: %h \n", $time, rst_n, a, b);

    #10;
    a = 256'd5_000_000;
    rst_n = 1;

    #10000;
    a = '1;
    rst_n = 0;

    #10;
    rst_n =1;

    #10000;

    rst_n = 0;
    
    $finish;
  end
endmodule

rtl/tb/waves/mod_q.vcd
$date
	Sun Mar 24 15:50:16 2024
$end
$version
	Icarus Verilog
$end
$timescale
	1s
$end
$scope module mod_q_tb $end
$var wire 256 ! b [255:0] $end
$var parameter 32 " N $end
$var reg 256 # a [255:0] $end
$var reg 1 $ clk $end
$var reg 1 % rst_n $end
$scope module U0 $end
$var wire 256 & a [255:0] $end
$var wire 1 $ clk $end
$var wire 1 % rst_n $end
$var wire 256 ' val [255:0] $end
$var wire 3 ( st [2:0] $end
$var wire 256 ) r [255:0] $end
$var wire 1 * dbz $end
$var wire 1 + data_rdy $end
$var parameter 32 , N $end
$var reg 256 - b [255:0] $end
$var reg 1 . busy $end
$var reg 256 / divd [255:0] $end
$var reg 256 0 q [255:0] $end
$scope module U0 $end
$var wire 1 $ clk $end
$var wire 1 * dbz $end
$var wire 256 1 divd [255:0] $end
$var wire 256 2 dvsr [255:0] $end
$var wire 1 % rst $end
$var wire 3 3 n_state [2:0] $end
$var parameter 32 4 N $end
$var parameter 2 5 active $end
$var parameter 2 6 done $end
$var parameter 2 7 reset $end
$var reg 257 8 acc [256:0] $end
$var reg 9 9 cnt [8:0] $end
$var reg 1 + data_rdy $end
$var reg 256 : quo [255:0] $end
$var reg 256 ; rem [255:0] $end
$var reg 3 < state [2:0] $end
$var reg 256 = val [255:0] $end
$scope begin division_alg $end
$upscope $end
$upscope $end
$upscope $end
$upscope $end
$enddefinitions $end
$comment Show the parameter values. $end
$dumpall
b0 7
b10 6
b1 5
b100000000 4
b100000000 ,
b100000000 "
$end
#0
$dumpvars
b0 =
b0 <
b0 ;
b0 :
b0 9
b0 8
b1 3
b111111111111111111111111111111111111111111111111111111111111111111111111111111111111111111111111111111111111111111111111111111111111111111111111111111111111111111111111111111111111111111111111111111111111111111111111111111111111111111111111111111111111111 2
b0 1
b111111111111111111111111111111111111111111111111111111111111111111111111111111111111111111111111111111111111111111111111111111111111111111111111111111111111111111111111111111111111111111111111111111111111111111111111111111111111111111111111111111111111111 0
b0 /
0.
b0 -
0+
0*
b0 )
b0 (
b0 '
b0 &
0%
0$
b0 #
b0 !
$end
#10
b1 (
b1 <
b1 9
b10011000100101101000000 /
b10011000100101101000000 1
1.
1%
b10011000100101101000000 #
b10011000100101101000000 &
1$
#20
0$
#30
b10 9
1$
#40
0$
#50
b11 9
1$
#60
0$
#70
b100 9
1$
#80
0$
#90
b101 9
1$
#100
0$
#110
b110 9
1$
#120
0$
#130
b111 9
1$
#140
0$
#150
b1000 9
1$
#160
0$
#170
b1001 9
1$
#180
0$
#190
b1010 9
1$
#200
0$
#210
b1011 9
1$
#220
0$
#230
b1100 9
1$
#240
0$
#250
b1101 9
1$
#260
0$
#270
b1110 9
1$
#280
0$
#290
b1111 9
1$
#300
0$
#310
b10000 9
1$
#320
0$
#330
b10001 9
1$
#340
0$
#350
b10010 9
1$
#360
0$
#370
b10011 9
1$
#380
0$
#390
b10100 9
1$
#400
0$
#410
b10101 9
1$
#420
0$
#430
b10110 9
1$
#440
0$
#450
b10111 9
1$
#460
0$
#470
b11000 9
1$
#480
0$
#490
b11001 9
1$
#500
0$
#510
b11010 9
1$
#520
0$
#530
b11011 9
1$
#540
0$
#550
b11100 9
1$
#560
0$
#570
b11101 9
1$
#580
0$
#590
b11110 9
1$
#600
0$
#610
b11111 9
1$
#620
0$
#630
b100000 9
1$
#640
0$
#650
b100001 9
1$
#660
0$
#670
b100010 9
1$
#680
0$
#690
b100011 9
1$
#700
0$
#710
b100100 9
1$
#720
0$
#730
b100101 9
1$
#740
0$
#750
b100110 9
1$
#760
0$
#770
b100111 9
1$
#780
0$
#790
b101000 9
1$
#800
0$
#810
b101001 9
1$
#820
0$
#830
b101010 9
1$
#840
0$
#850
b101011 9
1$
#860
0$
#870
b101100 9
1$
#880
0$
#890
b101101 9
1$
#900
0$
#910
b101110 9
1$
#920
0$
#930
b101111 9
1$
#940
0$
#950
b110000 9
1$
#960
0$
#970
b110001 9
1$
#980
0$
#990
b110010 9
1$
#1000
0$
#1010
b110011 9
1$
#1020
0$
#1030
b110100 9
1$
#1040
0$
#1050
b110101 9
1$
#1060
0$
#1070
b110110 9
1$
#1080
0$
#1090
b110111 9
1$
#1100
0$
#1110
b111000 9
1$
#1120
0$
#1130
b111001 9
1$
#1140
0$
#1150
b111010 9
1$
#1160
0$
#1170
b111011 9
1$
#1180
0$
#1190
b111100 9
1$
#1200
0$
#1210
b111101 9
1$
#1220
0$
#1230
b111110 9
1$
#1240
0$
#1250
b111111 9
1$
#1260
0$
#1270
b1000000 9
1$
#1280
0$
#1290
b1000001 9
1$
#1300
0$
#1310
b1000010 9
1$
#1320
0$
#1330
b1000011 9
1$
#1340
0$
#1350
b1000100 9
1$
#1360
0$
#1370
b1000101 9
1$
#1380
0$
#1390
b1000110 9
1$
#1400
0$
#1410
b1000111 9
1$
#1420
0$
#1430
b1001000 9
1$
#1440
0$
#1450
b1001001 9
1$
#1460
0$
#1470
b1001010 9
1$
#1480
0$
#1490
b1001011 9
1$
#1500
0$
#1510
b1001100 9
1$
#1520
0$
#1530
b1001101 9
1$
#1540
0$
#1550
b1001110 9
1$
#1560
0$
#1570
b1001111 9
1$
#1580
0$
#1590
b1010000 9
1$
#1600
0$
#1610
b1010001 9
1$
#1620
0$
#1630
b1010010 9
1$
#1640
0$
#1650
b1010011 9
1$
#1660
0$
#1670
b1010100 9
1$
#1680
0$
#1690
b1010101 9
1$
#1700
0$
#1710
b1010110 9
1$
#1720
0$
#1730
b1010111 9
1$
#1740
0$
#1750
b1011000 9
1$
#1760
0$
#1770
b1011001 9
1$
#1780
0$
#1790
b1011010 9
1$
#1800
0$
#1810
b1011011 9
1$
#1820
0$
#1830
b1011100 9
1$
#1840
0$
#1850
b1011101 9
1$
#1860
0$
#1870
b1011110 9
1$
#1880
0$
#1890
b1011111 9
1$
#1900
0$
#1910
b1100000 9
1$
#1920
0$
#1930
b1100001 9
1$
#1940
0$
#1950
b1100010 9
1$
#1960
0$
#1970
b1100011 9
1$
#1980
0$
#1990
b1100100 9
1$
#2000
0$
#2010
b1100101 9
1$
#2020
0$
#2030
b1100110 9
1$
#2040
0$
#2050
b1100111 9
1$
#2060
0$
#2070
b1101000 9
1$
#2080
0$
#2090
b1101001 9
1$
#2100
0$
#2110
b1101010 9
1$
#2120
0$
#2130
b1101011 9
1$
#2140
0$
#2150
b1101100 9
1$
#2160
0$
#2170
b1101101 9
1$
#2180
0$
#2190
b1101110 9
1$
#2200
0$
#2210
b1101111 9
1$
#2220
0$
#2230
b1110000 9
1$
#2240
0$
#2250
b1110001 9
1$
#2260
0$
#2270
b1110010 9
1$
#2280
0$
#2290
b1110011 9
1$
#2300
0$
#2310
b1110100 9
1$
#2320
0$
#2330
b1110101 9
1$
#2340
0$
#2350
b1110110 9
1$
#2360
0$
#2370
b1110111 9
1$
#2380
0$
#2390
b1111000 9
1$
#2400
0$
#2410
b1111001 9
1$
#2420
0$
#2430
b1111010 9
1$
#2440
0$
#2450
b1111011 9
1$
#2460
0$
#2470
b1111100 9
1$
#2480
0$
#2490
b1111101 9
1$
#2500
0$
#2510
b1111110 9
1$
#2520
0$
#2530
b1111111 9
1$
#2540
0$
#2550
b10000000 9
1$
#2560
0$
#2570
b10000001 9
1$
#2580
0$
#2590
b10000010 9
1$
#2600
0$
#2610
b10000011 9
1$
#2620
0$
#2630
b10000100 9
1$
#2640
0$
#2650
b10000101 9
1$
#2660
0$
#2670
b10000110 9
1$
#2680
0$
#2690
b10000111 9
1$
#2700
0$
#2710
b10001000 9
1$
#2720
0$
#2730
b10001001 9
1$
#2740
0$
#2750
b10001010 9
1$
#2760
0$
#2770
b10001011 9
1$
#2780
0$
#2790
b10001100 9
1$
#2800
0$
#2810
b10001101 9
1$
#2820
0$
#2830
b10001110 9
1$
#2840
0$
#2850
b10001111 9
1$
#2860
0$
#2870
b10010000 9
1$
#2880
0$
#2890
b10010001 9
1$
#2900
0$
#2910
b10010010 9
1$
#2920
0$
#2930
b10010011 9
1$
#2940
0$
#2950
b10010100 9
1$
#2960
0$
#2970
b10010101 9
1$
#2980
0$
#2990
b10010110 9
1$
#3000
0$
#3010
b10010111 9
1$
#3020
0$
#3030
b10011000 9
1$
#3040
0$
#3050
b10011001 9
1$
#3060
0$
#3070
b10011010 9
1$
#3080
0$
#3090
b10011011 9
1$
#3100
0$
#3110
b10011100 9
1$
#3120
0$
#3130
b10011101 9
1$
#3140
0$
#3150
b10011110 9
1$
#3160
0$
#3170
b10011111 9
1$
#3180
0$
#3190
b10100000 9
1$
#3200
0$
#3210
b10100001 9
1$
#3220
0$
#3230
b10100010 9
1$
#3240
0$
#3250
b10100011 9
1$
#3260
0$
#3270
b10100100 9
1$
#3280
0$
#3290
b10100101 9
1$
#3300
0$
#3310
b10100110 9
1$
#3320
0$
#3330
b10100111 9
1$
#3340
0$
#3350
b10101000 9
1$
#3360
0$
#3370
b10101001 9
1$
#3380
0$
#3390
b10101010 9
1$
#3400
0$
#3410
b10101011 9
1$
#3420
0$
#3430
b10101100 9
1$
#3440
0$
#3450
b10101101 9
1$
#3460
0$
#3470
b10101110 9
1$
#3480
0$
#3490
b10101111 9
1$
#3500
0$
#3510
b10110000 9
1$
#3520
0$
#3530
b10110001 9
1$
#3540
0$
#3550
b10110010 9
1$
#3560
0$
#3570
b10110011 9
1$
#3580
0$
#3590
b10110100 9
1$
#3600
0$
#3610
b10110101 9
1$
#3620
0$
#3630
b10110110 9
1$
#3640
0$
#3650
b10110111 9
1$
#3660
0$
#3670
b10111000 9
1$
#3680
0$
#3690
b10111001 9
1$
#3700
0$
#3710
b10111010 9
1$
#3720
0$
#3730
b10111011 9
1$
#3740
0$
#3750
b10111100 9
1$
#3760
0$
#3770
b10111101 9
1$
#3780
0$
#3790
b10111110 9
1$
#3800
0$
#3810
b10111111 9
1$
#3820
0$
#3830
b11000000 9
1$
#3840
0$
#3850
b11000001 9
1$
#3860
0$
#3870
b11000010 9
1$
#3880
0$
#3890
b11000011 9
1$
#3900
0$
#3910
b11000100 9
1$
#3920
0$
#3930
b11000101 9
1$
#3940
0$
#3950
b11000110 9
1$
#3960
0$
#3970
b11000111 9
1$
#3980
0$
#3990
b11001000 9
1$
#4000
0$
#4010
b11001001 9
1$
#4020
0$
#4030
b11001010 9
1$
#4040
0$
#4050
b11001011 9
1$
#4060
0$
#4070
b11001100 9
1$
#4080
0$
#4090
b11001101 9
1$
#4100
0$
#4110
b11001110 9
1$
#4120
0$
#4130
b11001111 9
1$
#4140
0$
#4150
b11010000 9
1$
#4160
0$
#4170
b11010001 9
1$
#4180
0$
#4190
b11010010 9
1$
#4200
0$
#4210
b11010011 9
1$
#4220
0$
#4230
b11010100 9
1$
#4240
0$
#4250
b11010101 9
1$
#4260
0$
#4270
b11010110 9
1$
#4280
0$
#4290
b11010111 9
1$
#4300
0$
#4310
b11011000 9
1$
#4320
0$
#4330
b11011001 9
1$
#4340
0$
#4350
b11011010 9
1$
#4360
0$
#4370
b11011011 9
1$
#4380
0$
#4390
b11011100 9
1$
#4400
0$
#4410
b11011101 9
1$
#4420
0$
#4430
b11011110 9
1$
#4440
0$
#4450
b11011111 9
1$
#4460
0$
#4470
b11100000 9
1$
#4480
0$
#4490
b11100001 9
1$
#4500
0$
#4510
b11100010 9
1$
#4520
0$
#4530
b11100011 9
1$
#4540
0$
#4550
b11100100 9
1$
#4560
0$
#4570
b11100101 9
1$
#4580
0$
#4590
b11100110 9
1$
#4600
0$
#4610
b11100111 9
1$
#4620
0$
#4630
b11101000 9
1$
#4640
0$
#4650
b11101001 9
1$
#4660
0$
#4670
b11101010 9
1$
#4680
0$
#4690
b1 8
b11101011 9
1$
#4700
0$
#4710
b10 8
b11101100 9
1$
#4720
0$
#4730
b100 8
b11101101 9
1$
#4740
0$
#4750
b1001 8
b11101110 9
1$
#4760
0$
#4770
b10011 8
b11101111 9
1$
#4780
0$
#4790
b100110 8
b11110000 9
1$
#4800
0$
#4810
b1001100 8
b11110001 9
1$
#4820
0$
#4830
b10011000 8
b11110010 9
1$
#4840
0$
#4850
b100110001 8
b11110011 9
1$
#4860
0$
#4870
b1001100010 8
b11110100 9
1$
#4880
0$
#4890
b10011000100 8
b11110101 9
1$
#4900
0$
#4910
b100110001001 8
b11110110 9
1$
#4920
0$
#4930
b1001100010010 8
b11110111 9
1$
#4940
0$
#4950
b10011000100101 8
b11111000 9
1$
#4960
0$
#4970
b100110001001011 8
b11111001 9
1$
#4980
0$
#4990
b1001100010010110 8
b11111010 9
1$
#5000
0$
#5010
b10011000100101101 8
b11111011 9
1$
#5020
0$
#5030
b100110001001011010 8
b11111100 9
1$
#5040
0$
#5050
b1001100010010110100 8
b11111101 9
1$
#5060
0$
#5070
b10011000100101101000 8
b11111110 9
1$
#5080
0$
#5090
b100110001001011010000 8
b11111111 9
1$
#5100
0$
#5110
b10 3
b1001100010010110100000 8
b100000000 9
1$
#5120
0$
#5130
b10011000100101101000000 8
b10 (
b10 <
b100000001 9
1$
#5140
0$
#5150
1+
b10011000100101101000000 )
b10011000100101101000000 ;
1$
